HISTORY.txt
MANIFEST.in
README.md
setup.py
rt/__init__.py
rt.topicembed.egg-info/PKG-INFO
rt.topicembed.egg-info/SOURCES.txt
rt.topicembed.egg-info/dependency_links.txt
rt.topicembed.egg-info/entry_points.txt
rt.topicembed.egg-info/namespace_packages.txt
rt.topicembed.egg-info/not-zip-safe
rt.topicembed.egg-info/requires.txt
rt.topicembed.egg-info/top_level.txt
rt/topicembed/__init__.py
rt/topicembed/configure.zcml
rt/topicembed/interfaces.py
rt/topicembed/browser/__init__.py
rt/topicembed/browser/configure.zcml
rt/topicembed/browser/embed.js.pt
rt/topicembed/browser/embed.py
rt/topicembed/browser/items_macro.pt
rt/topicembed/browser/topic_embed_form.pt
rt/topicembed/browser/resources/form.js
rt/topicembed/browser/resources/topic_embed.css
rt/topicembed/locales/rt.topicembed.pot
rt/topicembed/locales/it/LC_MESSAGES/rt.topicembed.po
rt/topicembed/profiles/default/actions.xml
rt/topicembed/profiles/default/browserlayer.xml
rt/topicembed/profiles/default/types/Topic.xml