Metadata-Version: 1.1
Name: rt.topicembed
Version: 1.3
Summary: Embed Plone's Topic results as Web Widget
Home-page: http://www.redturtle.it
Author: RedTurtle Team
Author-email: svilplone@redturtle.it
License: GPL
Keywords: plone topic embeded javascript
Platform: UNKNOWN
Classifier: Programming Language :: Python
